[
  {
    "CardID": 1,
    "CardName": "Strike",
    "Cost": 1,
    "imageUrl": "../texture/CARDS/strike.png",
    "Description": "Deal damage",
    "DefaultValue": 5
  },
  {
    "CardID": 2,
    "CardName": "Shield",
    "Cost": 1,
    "imageUrl": "../texture/CARDS/shield.png",
    "Description": "Increase defense until attacked",
    "DefaultValue": 5
  },
  {
    "CardID": 3,
    "CardName": "Heal",
    "Cost": 2,
    "imageUrl": "../texture/CARDS/heal.png",
    "Description": "Heal the character",
    "DefaultValue": 8
  },
  {
    "CardID": 4,
    "CardName": "Sweep",
    "Cost": 2,
    "imageUrl": "../texture/CARDS/sweep.png",
    "Description": "Deal damage to all enemies",
    "DefaultValue": 4
  },
  {
    "CardID": 5,
    "CardName": "Break",
    "Cost": 1,
    "imageUrl": "../texture/CARDS/break.png",
    "Description": "Deal damage,if target has shroud,get extra damage",
    "DefaultValue":4
  }

]
